README.txt
setup.py
Products/__init__.py
Products.PloneArticle.egg-info/PKG-INFO
Products.PloneArticle.egg-info/SOURCES.txt
Products.PloneArticle.egg-info/dependency_links.txt
Products.PloneArticle.egg-info/entry_points.txt
Products.PloneArticle.egg-info/namespace_packages.txt
Products.PloneArticle.egg-info/not-zip-safe
Products.PloneArticle.egg-info/requires.txt
Products.PloneArticle.egg-info/top_level.txt
Products/PloneArticle/ABOUT
Products/PloneArticle/CHANGES
Products/PloneArticle/LICENSE
Products/PloneArticle/README.txt
Products/PloneArticle/TESTED_WITH
Products/PloneArticle/TODO
Products/PloneArticle/__init__.py
Products/PloneArticle/__pkginfo__.py
Products/PloneArticle/adapters.zcml
Products/PloneArticle/browser.zcml
Products/PloneArticle/config.py
Products/PloneArticle/configure.zcml
Products/PloneArticle/deprecated.zcml
Products/PloneArticle/events.zcml
Products/PloneArticle/implements.zcml
Products/PloneArticle/pafti.py
Products/PloneArticle/profiles.zcml
Products/PloneArticle/setuphandlers.py
Products/PloneArticle/tool.gif
Products/PloneArticle/tool.py
Products/PloneArticle/utils.py
Products/PloneArticle/version.py
Products/PloneArticle/version.txt
Products/PloneArticle/Extensions/Install.py
Products/PloneArticle/Extensions/__init__.py
Products/PloneArticle/browser/__init__.py
Products/PloneArticle/browser/article.py
Products/PloneArticle/browser/explorer.py
Products/PloneArticle/browser/interface.py
Products/PloneArticle/browser/model.py
Products/PloneArticle/browser/modelsconfig.py
Products/PloneArticle/browser/multipage.py
Products/PloneArticle/browser/widgets.py
Products/PloneArticle/browser/templates/model_wrapper.pt
Products/PloneArticle/content/__init__.py
Products/PloneArticle/content/article.py
Products/PloneArticle/content/mixin.py
Products/PloneArticle/content/multipage.py
Products/PloneArticle/doc/FAQ
Products/PloneArticle/doc/SCREENSHOTS
Products/PloneArticle/doc/icon.png
Products/PloneArticle/doc/useCases/addACustomField-en.txt
Products/PloneArticle/doc/useCases/addACustomField-fr.txt
Products/PloneArticle/doc/useCases/addAttachment-en.txt
Products/PloneArticle/doc/useCases/addAttachment-fr.txt
Products/PloneArticle/doc/useCases/addDisplayModel-en.txt
Products/PloneArticle/doc/useCases/addImageToArticle-en.txt
Products/PloneArticle/doc/useCases/addImageToArticle-fr.txt
