Metadata-Version: 1.0
Name: Products.PloneArticle
Version: 4.2.0
Summary: A Plone document including images, attachments and links, with a free choice of layout.
Home-page: http://plone.org/products/plonearticle
Author: Ingeniweb
Author-email: support@ingeniweb.com
License: GPL
Keywords: plone
Platform: UNKNOWN
Classifier: Framework :: Plone
Classifier: Framework :: Plone :: 3.3
Classifier: Framework :: Plone :: 4.0
Classifier: Framework :: Plone :: 4.1
Classifier: Programming Language :: Python
Classifier: Topic :: Software Development :: Libraries :: Python Modules
